satzmetzger/TOKEN_DATEIENDUNGEN_IGNORECASE.PKL
satzmetzger/TOKEN_DOMAINSFINDEN.PKL
satzmetzger/TOKEN_REGEXABKUERZUNGEN.PKL
satzmetzger/TOKEN_VORHER.PKL
satzmetzger/__init__.py
satzmetzger/satzmetzger.py
satzmetzger-0.0.1.dist-info/LICENSE
satzmetzger-0.0.1.dist-info/METADATA
satzmetzger-0.0.1.dist-info/WHEEL
satzmetzger-0.0.1.dist-info/top_level.txt
satzmetzger-0.0.1.dist-info/RECORD
