Metadata-Version: 2.1
Name: satzmetzger
Version: 0.0.1
Summary: Split German text to sentence! Uses TRIE-Regex to filter ordinal numbers (23.04., 2.5. ...), roman numbers, (II., XI. ...) 15,000 abbreviations (z.B., Abk. ...) , about 7,500 second-level domains (.com.br, ac.at ...), 1500 file name extensions (hallo.docx, tabelle.xlsx ...)
Home-page: UNKNOWN
Author: Johannes Fischer -Hans Alemão-
Author-email: <deutschlernen@queroestudaralemao.com.br>
License: UNKNOWN
Keywords: nlp,spacy,German,pos
Platform: UNKNOWN
Classifier: Development Status :: 1 - Planning
Classifier: Programming Language :: Python :: 3
Requires-Dist: regex
